{
  "Locale": 18,
  "Version": 5,
  "Compressed": 0,
  "Reserved": "AAA=",
  "Entries": [
    {
      "Key": "0x28F6C433",
      "Value": "Управлять cимом"
    },
    {
      "Key": "0xB195FFA1",
      "Value": "Перестать управлять cимом"
    },
    {
      "Key": "0x098A53E9",
      "Value": "Вы используете «Управление любым симом» версии {0.String}, это экспериментальная предварительная версия!\\n\\nЭкспериментальные версии предназначены не для обычных игроков, а для тестирования новых функций и исправления ошибок!\\n\\nЕсли вы устанавили эту версию не намеренно, вам не следует используйте её!"
    },
    {
      "Key": "0x39BA3179",
      "Value": "Выйти из игры"
    },
    {
      "Key": "0x688D35BF",
      "Value": "Я знаю что делаю"
    },
    {
      "Key": "0x915E911B",
      "Value": "Управление любым симом - ПРИДУПРЕЖДЕНИЕ"
    },
    {
      "Key": "0x083C2912",
      "Value": "Добавить к соседям по комнате"
    },
    {
      "Key": "0xA7E24CAA",
      "Value": "Удалить у соседей по комнате"
    },
    {
      "Key": "0x284AD579",
      "Value": "Превратиться в NPC домовладельца"
    },
    {
      "Key": "0xDECE0085",
      "Value": "Превратиться в члена семьи"
    }
  ],
  "DataLength": "0x00000368",
  "Key": {
    "Type": "0x220557DA",
    "Group": "0x00000000",
    "Instance": "0x122152B569947D97"
  }
}
